metadsl_all/__init__.py
metadsl_all-0.1.0.dist-info/WHEEL
metadsl_all-0.1.0.dist-info/METADATA
metadsl_all-0.1.0.dist-info/RECORD
