Metadata-Version: 2.1
Name: metadsl_all
Version: 0.1.0
Summary: Metadsl meta package
Home-page: https://github.com/Quansight-Labs/metadsl
License: UNKNOWN
Author: Saul Shanabrook
Author-email: s.shanabrook@gmail.com
Classifier: Intended Audience :: Developers
Classifier: License :: OSI Approved :: BSD License
Classifier: Programming Language :: Python :: 3
Classifier: Programming Language :: Python :: 3.7
Classifier: Topic :: Software Development :: Libraries :: Python Modules
Requires-Dist: metadsl
Requires-Dist: metadsl_rewrite
Requires-Dist: metadsl_visualize
Requires-Dist: metadsl_numpy
Requires-Dist: metadsl_core
